invisible_ink.py
invisible_ink-0.1.1.dist-info/DESCRIPTION.rst
invisible_ink-0.1.1.dist-info/METADATA
invisible_ink-0.1.1.dist-info/RECORD
invisible_ink-0.1.1.dist-info/WHEEL
invisible_ink-0.1.1.dist-info/metadata.json
invisible_ink-0.1.1.dist-info/top_level.txt
