Metadata-Version: 2.0
Name: invisible-ink
Version: 0.1.1
Summary: Embedded messages in text for Python.
Home-page: https://github.com/dgouldin/invisible-ink
Author: David Gouldin
Author-email: david@gould.in
License: MIT
Platform: UNKNOWN
Classifier: Programming Language :: Python
Classifier: Programming Language :: Python :: 2.6
Classifier: Programming Language :: Python :: 2.7
Classifier: Programming Language :: Python :: Implementation :: CPython
Provides-Extra: tests
Requires-Dist: pytest (>=3.0.6,<3.1.0); extra == 'tests'
